monkez_qwidgets/__init__.py
monkez_qwidgets/widgets.py
monkez_qwidgets-0.1.0.dist-info/METADATA
monkez_qwidgets-0.1.0.dist-info/WHEEL
monkez_qwidgets-0.1.0.dist-info/top_level.txt
monkez_qwidgets-0.1.0.dist-info/RECORD
