Metadata-Version: 2.4
Name: monkez_qwidgets
Version: 0.1.0
Summary: My custom PyQt widgets
Author: Monkez
Author-email: tiendelai@gmail.com
Classifier: Programming Language :: Python :: 3
Classifier: Operating System :: OS Independent
Requires-Python: >=3.6
Requires-Dist: opencv-python
Requires-Dist: PyQt-Fluent-Widgets[full]
Dynamic: author
Dynamic: author-email
Dynamic: classifier
Dynamic: description
Dynamic: description-content-type
Dynamic: requires-dist
Dynamic: requires-python
Dynamic: summary
